luke/Preprocessing.py
luke/__init__.py
luke/defaults.py
luke/luke.py
luke/luke_cli.py
luke/luke_minigui.py
luke/luke_server.py
luke/docs/LICENSE
luke/docs/include.md
luke/docs/index.md
luke/docs/01-Getting-Started/01-Introduction.md
luke/docs/01-Getting-Started/02-Basics.md
luke/docs/01-Getting-Started/index.md
luke/docs/02-Components/01-Markdown-Overview.md
luke/docs/02-Components/02-Variables-and-Templates.md
luke/docs/02-Components/03-Attributes.md
luke/docs/02-Components/04-Sections.md
luke/docs/02-Components/05-Links-and-References.md
luke/docs/02-Components/06-Footnotes-and-Notes.md
luke/docs/02-Components/07-Lists.md
luke/docs/02-Components/08-Images.md
luke/docs/02-Components/09-Tables.md
luke/docs/02-Components/10-Blockquotes.md
luke/docs/02-Components/11-Math.md
luke/docs/02-Components/12-Code-and-Verbatim.md
luke/docs/02-Components/index.md
luke/docs/02-Components/test.md
luke/docs/03-Extra-Components/01-Card-Tables.md
luke/docs/03-Extra-Components/02-Tikz.md
luke/docs/03-Extra-Components/02-Tikz_0.svg
luke/docs/03-Extra-Components/03-Icons.md
luke/docs/03-Extra-Components/index.md
luke/docs/04-Commands/01-Control-Flow.md
luke/docs/04-Commands/02-Content-List.md
luke/docs/04-Commands/03-Predefined-Commands.md
luke/docs/04-Commands/04-Custom-Commands.md
luke/docs/04-Commands/index.md
luke/docs/05-Themes-and-Views/01-HTML.md
luke/docs/05-Themes-and-Views/02-Presentations.md
luke/docs/05-Themes-and-Views/03-LaTeX.md
luke/docs/05-Themes-and-Views/index.md
luke/docs/06-Extend/01-Define-Theme.md
luke/docs/06-Extend/02-Define-View.md
luke/docs/06-Extend/03-Define-Internal-Functions.md
luke/docs/06-Extend/index.md
luke/docs/07-Ecosystem/01-Docker-Image.md
luke/docs/07-Ecosystem/02-Integrate-as-Webserver.md
luke/docs/07-Ecosystem/index.md
luke/parser/__init__.py
luke/parser/markdown.py
luke/parser/compiled/lex.yy.c
luke/parser/compiled/markdown_parser.cp37-win_amd64.pyd
luke/parser/compiled/tmp.tab.c
luke/server/LiveReloadHandler.py
luke/server/MarkdownHandler.py
lukeparser-0.3.28.dist-info/LICENSE
lukeparser-0.3.28.dist-info/METADATA
lukeparser-0.3.28.dist-info/WHEEL
lukeparser-0.3.28.dist-info/entry_points.txt
lukeparser-0.3.28.dist-info/top_level.txt
lukeparser-0.3.28.dist-info/RECORD
