Metadata-Version: 2.1
Name: lukeparser
Version: 0.3.28
Summary: The Style of Markdown with the Power of LaTeX.
Home-page: https://lukeparser.github.io
Author: David Hartmann
Maintainer: David Hartmann
License: GPLv2
Project-URL: Documentation, https://lukeparser.github.io/lukeparser
Project-URL: Source, https://github.com/lukeparser/lukeparser/
Project-URL: Tracker, https://github.com/lukeparser/lukeparser/issues
Keywords: markdown,html,latex,parser
Platform: UNKNOWN
Classifier: Development Status :: 3 - Alpha
Classifier: Natural Language :: English
Classifier: License :: OSI Approved :: GNU General Public License v2 (GPLv2)
Classifier: Operating System :: MacOS :: MacOS X
Classifier: Operating System :: Microsoft :: Windows
Classifier: Operating System :: POSIX :: Linux
Classifier: Programming Language :: Python
Classifier: Programming Language :: Python :: 3 :: Only
Classifier: Programming Language :: Python :: 3
Classifier: Programming Language :: Python :: 3.7
Classifier: Programming Language :: Python :: 3.8
Classifier: Programming Language :: Python :: 3.9
Classifier: Programming Language :: Python :: 3.10
Classifier: Topic :: Software Development :: Libraries :: Python Modules
Classifier: Topic :: Text Processing
Requires-Python: >=3.7
License-File: LICENSE
Requires-Dist: pybison
Requires-Dist: watchdog
Requires-Dist: six
Requires-Dist: tqdm
Requires-Dist: tornado
Requires-Dist: livereload
